website_report/__init__.py
website_report/stats.py
website_report-1.0.1.dist-info/METADATA
website_report-1.0.1.dist-info/WHEEL
website_report-1.0.1.dist-info/top_level.txt
website_report-1.0.1.dist-info/RECORD
