Metadata-Version: 2.1
Name: website-report
Version: 1.0.1
Summary: a simple library that generates website reports
Home-page: https://github.com/behind24proxies/website_stats
Author: ICE-CREAM (Mike Lennon)
License: UNKNOWN
Keywords: python,website,website report,report,website performance,website stats
Platform: UNKNOWN
Classifier: Intended Audience :: Developers
Classifier: Programming Language :: Python :: 3
Classifier: Operating System :: Unix
Classifier: Operating System :: MacOS :: MacOS X
Classifier: Operating System :: Microsoft :: Windows
Requires-Dist: html-to-json
Requires-Dist: requests
